{
    "display": {
        "icon": {
            "item": "minecraft:emerald"
        },
        "title": "緑に輝く通貨",
        "description": "エメラルドを1st集める",
        "frame": "task",
        "show_toast": true,
        "announce_to_chat": true
    },
    "parent": "more_mining:more_advancement_mining/not_so_pickaxe",
    "criteria": {
        "requirement": {
            "trigger": "minecraft:inventory_changed",
            "conditions": {
                "player": {
                    "type": "minecraft:player"
                },
                "items": [
                    {
                        "items": [
                            "minecraft:emerald"
                        ],
                        "count": 64
                    }
                ]
            }
        }
    },
    "rewards": {
        "function": "more_mining:advancements_reward/green_money"
    }
}